{"doe": [{"box": {"width": 107, "x": 139, "name": "rect", "height": 27, "y": 451}, "label": "30/08/2031"}], "sex": [{"box": {"width": 67, "x": 350, "name": "rect", "height": 29, "y": 295}, "label": "Nam"}], "home": [{"box": {"width": 55, "x": 371, "name": "rect", "height": 30, "y": 342}, "label": "T\u00e2n"}, {"box": {"width": 75, "x": 427, "name": "rect", "height": 30, "y": 343}, "label": "Ph\u00fac"}, {"box": {"width": 69, "x": 515, "name": "rect", "height": 33, "y": 345}, "label": "Lang"}, {"box": {"width": 97, "x": 590, "name": "rect", "height": 31, "y": 344}, "label": "Ch\u00e1nh"}, {"box": {"width": 89, "x": 475, "name": "rect", "height": 28, "y": 373}, "label": "Thanh"}, {"box": {"width": 60, "x": 568, "name": "rect", "height": 26, "y": 378}, "label": "H\u00f3a"}], "ID": [{"box": {"width": 384, "x": 360, "name": "rect", "height": 46, "y": 119}, "label": "038091003182"}], "address": [{"box": {"width": 55, "x": 409, "name": "rect", "height": 33, "y": 401}, "label": "T\u00e2n"}, {"box": {"width": 72, "x": 469, "name": "rect", "height": 34, "y": 402}, "label": "Ph\u00fac"}, {"box": {"width": 72, "x": 555, "name": "rect", "height": 36, "y": 407}, "label": "Lang"}, {"box": {"width": 99, "x": 631, "name": "rect", "height": 28, "y": 412}, "label": "Ch\u00e1nh"}, {"box": {"width": 91, "x": 467, "name": "rect", "height": 29, "y": 445}, "label": "Thanh"}, {"box": {"width": 61, "x": 563, "name": "rect", "height": 30, "y": 446}, "label": "H\u00f3a"}], "DOB": [{"box": {"width": 156, "x": 492, "name": "rect", "height": 29, "y": 254}, "label": "30/08/1991"}], "file": "16129171_01654356645_CMND_MatTruoc.jpg", "name": [{"box": {"width": 46, "x": 434, "name": "rect", "height": 33, "y": 213}, "label": "H\u00c0"}, {"box": {"width": 68, "x": 485, "name": "rect", "height": 35, "y": 212}, "label": "V\u0102N"}, {"box": {"width": 100, "x": 555, "name": "rect", "height": 34, "y": 212}, "label": "\u0110ANG"}]}