{"file": "16241312_0988283510_CMND_MatTruoc.jpg", "ID": [{"label": "036085007832", "box": {"name": "rect", "x": 348, "y": 135, "width": 328, "height": 40}}], "name": [{"label": "TR\u01af\u01a0NG", "box": {"name": "rect", "x": 370, "y": 204, "width": 128, "height": 34}}, {"label": "V\u0102N", "box": {"name": "rect", "x": 496, "y": 205, "width": 62, "height": 32}}, {"label": "S\u01a0N", "box": {"name": "rect", "x": 560, "y": 206, "width": 63, "height": 33}}], "DOB": [{"label": "04/10/1985", "box": {"name": "rect", "x": 469, "y": 253, "width": 155, "height": 33}}], "doe": [{"label": "04/10/2025", "box": {"name": "rect", "x": 159, "y": 459, "width": 132, "height": 28}}], "sex": [{"label": "Nam", "box": {"name": "rect", "x": 349, "y": 290, "width": 71, "height": 32}}], "home": [{"label": "Y\u00ean", "box": {"name": "rect", "x": 372, "y": 364, "width": 54, "height": 34}}, {"label": "Ninh", "box": {"name": "rect", "x": 427, "y": 362, "width": 56, "height": 38}}, {"label": "\u00dd", "box": {"name": "rect", "x": 490, "y": 364, "width": 28, "height": 34}}, {"label": "Y\u00ean", "box": {"name": "rect", "x": 520, "y": 366, "width": 47, "height": 33}}, {"label": "Nam", "box": {"name": "rect", "x": 575, "y": 369, "width": 63, "height": 30}}, {"label": "\u0110\u1ecbnh", "box": {"name": "rect", "x": 640, "y": 369, "width": 61, "height": 29}}], "address": [{"label": "Y\u00ean", "box": {"name": "rect", "x": 370, "y": 439, "width": 57, "height": 34}}, {"label": "Ninh", "box": {"name": "rect", "x": 428, "y": 439, "width": 60, "height": 34}}, {"label": "\u00dd", "box": {"name": "rect", "x": 495, "y": 436, "width": 24, "height": 34}}, {"label": "Y\u00ean", "box": {"name": "rect", "x": 522, "y": 441, "width": 49, "height": 33}}, {"label": "Nam", "box": {"name": "rect", "x": 580, "y": 443, "width": 63, "height": 32}}, {"label": "\u0110inh", "box": {"name": "rect", "x": 643, "y": 443, "width": 59, "height": 34}}]}