{"doe": [{"box": {"width": 103, "x": 157, "name": "rect", "height": 23, "y": 465}, "label": "06/11/2022"}], "sex": [{"box": {"width": 63, "x": 363, "name": "rect", "height": 25, "y": 312}, "label": "Nam"}], "home": [{"box": {"width": 80, "x": 304, "name": "rect", "height": 27, "y": 388}, "label": "Quang"}, {"box": {"width": 74, "x": 390, "name": "rect", "height": 29, "y": 389}, "label": "Trung"}, {"box": {"width": 67, "x": 478, "name": "rect", "height": 27, "y": 388}, "label": "Ng\u1ecdc"}, {"box": {"width": 46, "x": 553, "name": "rect", "height": 24, "y": 390}, "label": "L\u1eb7c"}, {"box": {"width": 81, "x": 612, "name": "rect", "height": 29, "y": 388}, "label": "Thanh"}, {"box": {"width": 53, "x": 701, "name": "rect", "height": 26, "y": 391}, "label": "H\u00f3a"}], "ID": [{"box": {"width": 351, "x": 351, "name": "rect", "height": 34, "y": 133}, "label": "038062005410"}], "address": [{"box": {"width": 83, "x": 375, "name": "rect", "height": 26, "y": 423}, "label": "Quang"}, {"box": {"width": 55, "x": 465, "name": "rect", "height": 23, "y": 423}, "label": "S\u01a1n"}, {"box": {"width": 82, "x": 288, "name": "rect", "height": 28, "y": 456}, "label": "Quang"}, {"box": {"width": 70, "x": 378, "name": "rect", "height": 29, "y": 458}, "label": "Trung"}, {"box": {"width": 64, "x": 465, "name": "rect", "height": 26, "y": 460}, "label": "Ng\u1ecdc"}, {"box": {"width": 45, "x": 539, "name": "rect", "height": 25, "y": 461}, "label": "L\u1eb7c"}, {"box": {"width": 82, "x": 594, "name": "rect", "height": 26, "y": 462}, "label": "Thanh"}, {"box": {"width": 53, "x": 683, "name": "rect", "height": 26, "y": 462}, "label": "H\u00f3a"}], "DOB": [{"box": {"width": 144, "x": 501, "name": "rect", "height": 29, "y": 268}, "label": "06/11/1962"}], "file": "16405101_01676696132_CMND_MatTruoc.jpg", "name": [{"box": {"width": 66, "x": 483, "name": "rect", "height": 29, "y": 192}, "label": "CAO"}, {"box": {"width": 66, "x": 554, "name": "rect", "height": 29, "y": 192}, "label": "V\u0102N"}, {"box": {"width": 115, "x": 623, "name": "rect", "height": 29, "y": 190}, "label": "V\u01af\u01a0NG"}]}