{"file": "16405878_0934974480_CMND_MatTruoc.jpg", "ID": [{"label": "066179000004", "box": {"name": "rect", "x": 368, "y": 137, "width": 342, "height": 40}}], "name": [{"label": "PHA\u0323M", "box": {"name": "rect", "x": 425, "y": 214, "width": 91, "height": 35}}, {"label": "THI\u0323", "box": {"name": "rect", "x": 521, "y": 212, "width": 49, "height": 33}}, {"label": "THI", "box": {"name": "rect", "x": 572, "y": 213, "width": 47, "height": 35}}], "DOB": [{"label": "20/10/1979", "box": {"name": "rect", "x": 483, "y": 295, "width": 139, "height": 29}}], "doe": [{"label": "29/12/2030", "box": {"name": "rect", "x": 143, "y": 460, "width": 133, "height": 25}}], "sex": [{"label": "N\u01b0\u0303", "box": {"name": "rect", "x": 351, "y": 333, "width": 49, "height": 27}}], "home": [{"label": "Nam", "box": {"name": "rect", "x": 452, "y": 359, "width": 60, "height": 34}}], "address": [{"label": "40", "box": {"name": "rect", "x": 403, "y": 416, "width": 37, "height": 36}}, {"label": "\u0110\u01b0\u01a1\u0300ng", "box": {"name": "rect", "x": 445, "y": 424, "width": 87, "height": 30}}, {"label": "6A", "box": {"name": "rect", "x": 537, "y": 424, "width": 38, "height": 29}}, {"label": "KP3", "box": {"name": "rect", "x": 585, "y": 419, "width": 52, "height": 31}}, {"label": "Ph\u01b0\u01a1\u0301c", "box": {"name": "rect", "x": 301, "y": 453, "width": 88, "height": 31}}, {"label": "Bi\u0300nh", "box": {"name": "rect", "x": 393, "y": 453, "width": 57, "height": 31}}, {"label": "Qu\u00e2\u0323n", "box": {"name": "rect", "x": 461, "y": 455, "width": 70, "height": 25}}, {"label": "9", "box": {"name": "rect", "x": 535, "y": 451, "width": 21, "height": 31}}, {"label": "Tp", "box": {"name": "rect", "x": 566, "y": 454, "width": 31, "height": 31}}, {"label": "H\u00f4\u0300", "box": {"name": "rect", "x": 601, "y": 448, "width": 41, "height": 33}}, {"label": "Chi\u0301", "box": {"name": "rect", "x": 644, "y": 444, "width": 45, "height": 39}}, {"label": "Minh", "box": {"name": "rect", "x": 693, "y": 445, "width": 56, "height": 46}}]}