{"doe": [{"box": {"width": 139, "x": 479, "name": "rect", "height": 38, "y": 308}, "label": "14/04/1962"}], "sex": [{"box": {"width": 64, "x": 352, "name": "rect", "height": 31, "y": 347}, "label": "Nam"}], "home": [{"box": {"width": 85, "x": 420, "name": "rect", "height": 37, "y": 373}, "label": "Qu\u1ea3ng"}, {"box": {"width": 90, "x": 507, "name": "rect", "height": 32, "y": 377}, "label": "\u0110\u00f4ng"}, {"box": {"width": 81, "x": 600, "name": "rect", "height": 32, "y": 376}, "label": "Thanh"}, {"box": {"width": 57, "x": 683, "name": "rect", "height": 31, "y": 373}, "label": "H\u00f3a"}], "ID": [{"box": {"width": 336, "x": 362, "name": "rect", "height": 46, "y": 136}, "label": "001062002105"}], "address": [{"box": {"width": 112, "x": 532, "name": "rect", "height": 32, "y": 435}, "label": "101-K3B"}, {"box": {"width": 68, "x": 388, "name": "rect", "height": 29, "y": 470}, "label": "B\u00e1ch"}, {"box": {"width": 65, "x": 458, "name": "rect", "height": 27, "y": 470}, "label": "Khoa"}, {"box": {"width": 44, "x": 533, "name": "rect", "height": 30, "y": 469}, "label": "Hai"}, {"box": {"width": 36, "x": 579, "name": "rect", "height": 29, "y": 469}, "label": "B\u00e0"}, {"box": {"width": 77, "x": 615, "name": "rect", "height": 30, "y": 468}, "label": "Tr\u01b0ng"}, {"box": {"width": 41, "x": 697, "name": "rect", "height": 31, "y": 463}, "label": "H\u00e0"}, {"box": {"width": 44, "x": 739, "name": "rect", "height": 31, "y": 464}, "label": "N\u1ed9i"}], "DOB": [{"box": {"width": 139, "x": 479, "name": "rect", "height": 38, "y": 308}, "label": "14/04/1962"}], "file": "16577014_0986134751_CMND_MatTruoc.jpg", "name": [{"box": {"width": 50, "x": 402, "name": "rect", "height": 35, "y": 216}, "label": "L\u1ea0I"}, {"box": {"width": 118, "x": 454, "name": "rect", "height": 35, "y": 213}, "label": "NGUY\u00caN"}, {"box": {"width": 69, "x": 576, "name": "rect", "height": 36, "y": 212}, "label": "TI\u1ebeN"}]}