{"doe": [{"box": {"width": 110, "x": 173, "name": "rect", "height": 23, "y": 476}, "label": "03/11/2021"}], "sex": [{"box": {"width": 61, "x": 355, "name": "rect", "height": 27, "y": 317}, "label": "Nam"}], "home": [], "ID": [{"box": {"width": 334, "x": 364, "name": "rect", "height": 43, "y": 139}, "label": "030096001350"}], "address": [{"box": {"width": 49, "x": 369, "name": "rect", "height": 27, "y": 366}, "label": "T\u00e2n"}, {"box": {"width": 49, "x": 422, "name": "rect", "height": 27, "y": 366}, "label": "D\u00e2n"}, {"box": {"width": 44, "x": 512, "name": "rect", "height": 26, "y": 428}, "label": "Ch\u00ed"}, {"box": {"width": 53, "x": 560, "name": "rect", "height": 24, "y": 433}, "label": "Linh"}, {"box": {"width": 43, "x": 624, "name": "rect", "height": 27, "y": 431}, "label": "H\u1ea3i"}, {"box": {"width": 91, "x": 674, "name": "rect", "height": 29, "y": 436}, "label": "D\u01b0\u01a1ng"}, {"box": {"width": 47, "x": 412, "name": "rect", "height": 24, "y": 429}, "label": "Sao"}, {"box": {"width": 41, "x": 460, "name": "rect", "height": 28, "y": 427}, "label": "\u0110\u1ecf"}, {"box": {"width": 44, "x": 482, "name": "rect", "height": 26, "y": 367}, "label": "Ch\u00ed"}, {"box": {"width": 53, "x": 533, "name": "rect", "height": 24, "y": 370}, "label": "Linh"}, {"box": {"width": 43, "x": 599, "name": "rect", "height": 27, "y": 369}, "label": "H\u1ea3i"}, {"box": {"width": 91, "x": 647, "name": "rect", "height": 29, "y": 373}, "label": "D\u01b0\u01a1ng"}], "DOB": [{"box": {"width": 140, "x": 478, "name": "rect", "height": 30, "y": 275}, "label": "03/11/1996"}], "file": "16622762_0866431696_CMND_MatTruoc.jpg", "name": [{"box": {"width": 37, "x": 399, "name": "rect", "height": 35, "y": 221}, "label": "L\u00ca"}, {"box": {"width": 65, "x": 442, "name": "rect", "height": 35, "y": 223}, "label": "\u0110\u00c0O"}, {"box": {"width": 67, "x": 509, "name": "rect", "height": 29, "y": 228}, "label": "NAM"}, {"box": {"width": 67, "x": 579, "name": "rect", "height": 28, "y": 227}, "label": "LINH"}]}