{"file": "16668612_01695494359_CMND_MatTruoc.jpg", "ID": [{"label": "052098000008", "box": {"name": "rect", "x": 370, "y": 132, "width": 352, "height": 48}}], "name": [{"label": "TR\u1ea6N", "box": {"name": "rect", "x": 406, "y": 193, "width": 85, "height": 38}}, {"label": "QUANG", "box": {"name": "rect", "x": 496, "y": 197, "width": 103, "height": 31}}, {"label": "L\u1ed8C", "box": {"name": "rect", "x": 607, "y": 195, "width": 61, "height": 38}}], "DOB": [{"label": "25/10/1998", "box": {"name": "rect", "x": 478, "y": 269, "width": 146, "height": 36}}], "doe": [{"label": "25/10/2023", "box": {"name": "rect", "x": 167, "y": 461, "width": 115, "height": 32}}], "sex": [{"label": "Nam", "box": {"name": "rect", "x": 356, "y": 320, "width": 65, "height": 25}}], "home": [{"label": "B\u00ecnh", "box": {"name": "rect", "x": 364, "y": 356, "width": 67, "height": 29}}, {"label": "\u0110\u1ecbnh", "box": {"name": "rect", "x": 432, "y": 357, "width": 63, "height": 33}}], "address": [{"label": "162/144/4", "box": {"name": "rect", "x": 411, "y": 421, "width": 125, "height": 27}}, {"label": "Nguy\u1ec5n", "box": {"name": "rect", "x": 543, "y": 417, "width": 96, "height": 35}}, {"label": "Duy", "box": {"name": "rect", "x": 640, "y": 417, "width": 55, "height": 35}}, {"label": "Cung", "box": {"name": "rect", "x": 697, "y": 417, "width": 64, "height": 35}}, {"label": "Ph\u01b0\u1eddng", "box": {"name": "rect", "x": 301, "y": 453, "width": 104, "height": 33}}, {"label": "12", "box": {"name": "rect", "x": 412, "y": 457, "width": 35, "height": 35}}, {"label": "G\u00f2", "box": {"name": "rect", "x": 452, "y": 453, "width": 40, "height": 31}}, {"label": "V\u1ea5p", "box": {"name": "rect", "x": 496, "y": 452, "width": 53, "height": 39}}, {"label": "TP", "box": {"name": "rect", "x": 552, "y": 455, "width": 48, "height": 32}}, {"label": "H\u1ed3", "box": {"name": "rect", "x": 609, "y": 455, "width": 37, "height": 33}}, {"label": "Ch\u00ed", "box": {"name": "rect", "x": 651, "y": 457, "width": 47, "height": 28}}, {"label": "Minh", "box": {"name": "rect", "x": 700, "y": 457, "width": 64, "height": 28}}]}