{"doe": [{"box": {"width": 123, "x": 176, "name": "rect", "height": 40, "y": 448}, "label": "17/11/2024"}], "sex": [{"box": {"width": 67, "x": 363, "name": "rect", "height": 30, "y": 293}, "label": "Nam"}], "home": [{"box": {"width": 40, "x": 375, "name": "rect", "height": 34, "y": 336}, "label": "L\u00ea"}, {"box": {"width": 42, "x": 418, "name": "rect", "height": 34, "y": 337}, "label": "L\u1ee3i"}, {"box": {"width": 46, "x": 468, "name": "rect", "height": 40, "y": 333}, "label": "Ng\u00f4"}, {"box": {"width": 78, "x": 518, "name": "rect", "height": 36, "y": 341}, "label": "Quy\u1ec1n"}, {"box": {"width": 40, "x": 603, "name": "rect", "height": 40, "y": 336}, "label": "H\u1ea3i"}, {"box": {"width": 71, "x": 649, "name": "rect", "height": 39, "y": 335}, "label": "Ph\u00f2ng"}], "ID": [{"box": {"width": 334, "x": 357, "name": "rect", "height": 36, "y": 144}, "label": "079084010500"}], "address": [{"box": {"width": 110, "x": 393, "name": "rect", "height": 29, "y": 395}, "label": "788/58B"}, {"box": {"width": 83, "x": 509, "name": "rect", "height": 33, "y": 397}, "label": "Nguy\u1ec5n"}, {"box": {"width": 68, "x": 598, "name": "rect", "height": 36, "y": 396}, "label": "Ki\u1ec7m"}, {"box": {"width": 103, "x": 322, "name": "rect", "height": 46, "y": 428}, "label": "Ph\u01b0\u1eddng"}, {"box": {"width": 25, "x": 431, "name": "rect", "height": 32, "y": 436}, "label": "3"}, {"box": {"width": 36, "x": 460, "name": "rect", "height": 29, "y": 438}, "label": "G\u00f2"}, {"box": {"width": 46, "x": 500, "name": "rect", "height": 34, "y": 435}, "label": "V\u1ea5p"}, {"box": {"width": 39, "x": 553, "name": "rect", "height": 32, "y": 435}, "label": "TP"}, {"box": {"width": 33, "x": 602, "name": "rect", "height": 35, "y": 437}, "label": "H\u1ed3"}, {"box": {"width": 42, "x": 640, "name": "rect", "height": 35, "y": 434}, "label": "Ch\u00ed"}, {"box": {"width": 63, "x": 683, "name": "rect", "height": 40, "y": 433}, "label": "Minh"}], "DOB": [{"box": {"width": 182, "x": 484, "name": "rect", "height": 26, "y": 259}, "label": "17/11/1984"}], "file": "16819262_0522908272_CMND_MatTruoc.jpg", "name": [{"box": {"width": 47, "x": 395, "name": "rect", "height": 32, "y": 212}, "label": "L\u00ca"}, {"box": {"width": 95, "x": 443, "name": "rect", "height": 32, "y": 214}, "label": "HO\u00c0NG"}, {"box": {"width": 81, "x": 543, "name": "rect", "height": 31, "y": 211}, "label": "MINH"}]}