{"doe": [{"box": {"width": 108, "x": 182, "name": "rect", "height": 34, "y": 461}, "label": "03/01/2028"}], "sex": [{"box": {"width": 58, "x": 362, "name": "rect", "height": 32, "y": 308}, "label": "Nam"}], "home": [{"box": {"width": 60, "x": 372, "name": "rect", "height": 33, "y": 355}, "label": "Th\u1ee7y"}, {"box": {"width": 93, "x": 437, "name": "rect", "height": 35, "y": 356}, "label": "Nguy\u00ean"}, {"box": {"width": 43, "x": 537, "name": "rect", "height": 35, "y": 357}, "label": "H\u1ea3i"}, {"box": {"width": 82, "x": 588, "name": "rect", "height": 34, "y": 362}, "label": "Ph\u00f2ng"}], "ID": [{"box": {"width": 333, "x": 371, "name": "rect", "height": 40, "y": 134}, "label": "022068001006"}], "address": [{"box": {"width": 35, "x": 415, "name": "rect", "height": 31, "y": 415}, "label": "T\u1ed5"}, {"box": {"width": 19, "x": 449, "name": "rect", "height": 30, "y": 418}, "label": "9"}, {"box": {"width": 52, "x": 473, "name": "rect", "height": 30, "y": 419}, "label": "Khu"}, {"box": {"width": 19, "x": 524, "name": "rect", "height": 30, "y": 418}, "label": "1"}, {"box": {"width": 68, "x": 554, "name": "rect", "height": 31, "y": 419}, "label": "B\u1ea1ch"}, {"box": {"width": 71, "x": 619, "name": "rect", "height": 38, "y": 418}, "label": "\u0110\u1eb1ng"}, {"box": {"width": 36, "x": 405, "name": "rect", "height": 35, "y": 453}, "label": "H\u1ea1"}, {"box": {"width": 58, "x": 446, "name": "rect", "height": 28, "y": 458}, "label": "Long"}, {"box": {"width": 85, "x": 512, "name": "rect", "height": 31, "y": 457}, "label": "Qu\u1ea3ng"}, {"box": {"width": 57, "x": 600, "name": "rect", "height": 30, "y": 458}, "label": "Ninh"}], "DOB": [{"box": {"width": 138, "x": 484, "name": "rect", "height": 31, "y": 269}, "label": "03/01/1968"}], "file": "16818481_0522911288_CMND_MatTruoc.jpg", "name": [{"box": {"width": 123, "x": 367, "name": "rect", "height": 36, "y": 214}, "label": "NGUY\u1ec4N"}, {"box": {"width": 82, "x": 488, "name": "rect", "height": 40, "y": 214}, "label": "XU\u00c2N"}, {"box": {"width": 113, "x": 572, "name": "rect", "height": 39, "y": 215}, "label": "C\u01af\u1edeNG"}]}