{"file": "2511924_0928292109_CMND_MatTruoc.jpg", "ID": [{"label": "03109004172", "box": {"name": "rect", "x": 350, "y": 130, "width": 353, "height": 51}}], "name": [{"label": "TR\u00c2\u0300N", "box": {"name": "rect", "x": 450, "y": 203, "width": 84, "height": 40}}, {"label": "V\u0102N", "box": {"name": "rect", "x": 534, "y": 204, "width": 68, "height": 37}}, {"label": "\u0110A\u0323I", "box": {"name": "rect", "x": 602, "y": 203, "width": 57, "height": 41}}], "DOB": [{"label": "29/08/1991", "box": {"name": "rect", "x": 467, "y": 253, "width": 145, "height": 37}}], "doe": [{"label": "29/08/2031", "box": {"name": "rect", "x": 140, "y": 458, "width": 137, "height": 35}}], "sex": [{"label": "Nam", "box": {"name": "rect", "x": 342, "y": 305, "width": 64, "height": 32}}], "home": [{"label": "\u0110a\u0323i", "box": {"name": "rect", "x": 350, "y": 344, "width": 52, "height": 35}}, {"label": "Th\u0103\u0301ng", "box": {"name": "rect", "x": 402, "y": 342, "width": 78, "height": 38}}, {"label": "Ti\u00ean", "box": {"name": "rect", "x": 488, "y": 340, "width": 63, "height": 36}}, {"label": "La\u0303ng", "box": {"name": "rect", "x": 555, "y": 346, "width": 61, "height": 30}}, {"label": "Ha\u0309i", "box": {"name": "rect", "x": 454, "y": 377, "width": 54, "height": 28}}, {"label": "Pho\u0300ng", "box": {"name": "rect", "x": 508, "y": 376, "width": 78, "height": 32}}], "address": [{"label": "\u0110a\u0323i", "box": {"name": "rect", "x": 393, "y": 410, "width": 46, "height": 34}}, {"label": "Th\u0103\u0301ng", "box": {"name": "rect", "x": 439, "y": 408, "width": 81, "height": 31}}, {"label": "Ti\u00ean", "box": {"name": "rect", "x": 529, "y": 404, "width": 62, "height": 33}}, {"label": "La\u0303ng", "box": {"name": "rect", "x": 589, "y": 409, "width": 71, "height": 29}}, {"label": "Ha\u0309i", "box": {"name": "rect", "x": 450, "y": 442, "width": 51, "height": 32}}, {"label": "Pho\u0300ng", "box": {"name": "rect", "x": 501, "y": 439, "width": 83, "height": 39}}]}