{"doe": [{"box": {"width": 121, "x": 175, "name": "rect", "height": 24, "y": 454}, "label": "01/01/2020"}], "sex": [{"box": {"width": 43, "x": 361, "name": "rect", "height": 30, "y": 301}, "label": "N\u1eef"}], "home": [{"box": {"width": 44, "x": 374, "name": "rect", "height": 35, "y": 338}, "label": "\u0110\u1ea5t"}, {"box": {"width": 38, "x": 416, "name": "rect", "height": 29, "y": 340}, "label": "\u0110\u1ecf"}, {"box": {"width": 34, "x": 458, "name": "rect", "height": 25, "y": 343}, "label": "B\u00e0"}, {"box": {"width": 43, "x": 497, "name": "rect", "height": 32, "y": 342}, "label": "R\u1ecba"}, {"box": {"width": 62, "x": 554, "name": "rect", "height": 28, "y": 344}, "label": "V\u0169ng"}, {"box": {"width": 46, "x": 619, "name": "rect", "height": 27, "y": 342}, "label": "T\u00e0u"}], "ID": [{"box": {"width": 320, "x": 361, "name": "rect", "height": 41, "y": 142}, "label": "077180000332"}], "address": [{"box": {"width": 44, "x": 376, "name": "rect", "height": 35, "y": 426}, "label": "\u0110\u1ea5t"}, {"box": {"width": 38, "x": 421, "name": "rect", "height": 29, "y": 429}, "label": "\u0110\u1ecf"}, {"box": {"width": 34, "x": 464, "name": "rect", "height": 25, "y": 431}, "label": "B\u00e0"}, {"box": {"width": 43, "x": 498, "name": "rect", "height": 32, "y": 429}, "label": "R\u1ecba"}, {"box": {"width": 62, "x": 557, "name": "rect", "height": 28, "y": 435}, "label": "V\u0169ng"}, {"box": {"width": 46, "x": 620, "name": "rect", "height": 27, "y": 433}, "label": "T\u00e0u"}, {"box": {"width": 32, "x": 411, "name": "rect", "height": 30, "y": 395}, "label": "KP"}, {"box": {"width": 78, "x": 451, "name": "rect", "height": 26, "y": 397}, "label": "Ph\u01b0\u1edbc"}, {"box": {"width": 68, "x": 534, "name": "rect", "height": 32, "y": 399}, "label": "Trung"}, {"box": {"width": 80, "x": 612, "name": "rect", "height": 30, "y": 400}, "label": "Ph\u01b0\u1edbc"}, {"box": {"width": 44, "x": 695, "name": "rect", "height": 28, "y": 400}, "label": "H\u1ea3i"}], "DOB": [{"box": {"width": 129, "x": 476, "name": "rect", "height": 27, "y": 261}, "label": "01/01/1980"}], "file": "2615127_0928750680_CMND_MatTruoc.jpg", "name": [{"box": {"width": 75, "x": 410, "name": "rect", "height": 27, "y": 214}, "label": "TR\u1ea6N"}, {"box": {"width": 44, "x": 487, "name": "rect", "height": 32, "y": 216}, "label": "TH\u1eca"}, {"box": {"width": 80, "x": 530, "name": "rect", "height": 29, "y": 215}, "label": "H\u1ed2NG"}, {"box": {"width": 86, "x": 612, "name": "rect", "height": 34, "y": 214}, "label": "TRINH"}]}