{"doe": [{"box": {"width": 112, "x": 182, "name": "rect", "height": 22, "y": 464}, "label": "14/10/2025"}], "sex": [{"box": {"width": 60, "x": 373, "name": "rect", "height": 21, "y": 305}, "label": "Nam"}], "home": [{"box": {"width": 62, "x": 496, "name": "rect", "height": 27, "y": 348}, "label": "Nam"}, {"box": {"width": 61, "x": 562, "name": "rect", "height": 31, "y": 347}, "label": "\u0110\u1ecbnh"}], "ID": [{"box": {"width": 335, "x": 374, "name": "rect", "height": 40, "y": 130}, "label": "001085019599"}], "address": [{"box": {"width": 38, "x": 506, "name": "rect", "height": 28, "y": 408}, "label": "26"}, {"box": {"width": 34, "x": 548, "name": "rect", "height": 30, "y": 404}, "label": "T\u1ed5"}, {"box": {"width": 18, "x": 588, "name": "rect", "height": 26, "y": 409}, "label": "2"}, {"box": {"width": 61, "x": 374, "name": "rect", "height": 31, "y": 447}, "label": "L\u00e1ng"}, {"box": {"width": 105, "x": 439, "name": "rect", "height": 32, "y": 446}, "label": "Th\u01b0\u1ee3ng"}, {"box": {"width": 71, "x": 551, "name": "rect", "height": 35, "y": 442}, "label": "\u0110\u1ed1ng"}, {"box": {"width": 40, "x": 626, "name": "rect", "height": 27, "y": 446}, "label": "\u0110a"}, {"box": {"width": 39, "x": 675, "name": "rect", "height": 28, "y": 442}, "label": "H\u00e0"}, {"box": {"width": 45, "x": 717, "name": "rect", "height": 33, "y": 442}, "label": "N\u1ed9i"}], "DOB": [{"box": {"width": 143, "x": 501, "name": "rect", "height": 25, "y": 262}, "label": "14/10/1985"}], "file": "3175904_0923185790_CMND_MatTruoc.jpg", "name": [{"box": {"width": 87, "x": 419, "name": "rect", "height": 33, "y": 210}, "label": "\u0110O\u00c0N"}, {"box": {"width": 66, "x": 510, "name": "rect", "height": 28, "y": 210}, "label": "TH\u00c1I"}, {"box": {"width": 82, "x": 582, "name": "rect", "height": 29, "y": 208}, "label": "T\u00d9NG"}]}