{"doe": [{"box": {"width": 130, "x": 153, "name": "rect", "height": 27, "y": 458}, "label": "26/03/2020"}], "sex": [{"box": {"width": 41, "x": 355, "name": "rect", "height": 29, "y": 297}, "label": "N\u1eef"}], "home": [{"box": {"width": 101, "x": 365, "name": "rect", "height": 37, "y": 343}, "label": "Ch\u01b0\u01a1ng"}, {"box": {"width": 35, "x": 469, "name": "rect", "height": 31, "y": 348}, "label": "M\u1ef9"}, {"box": {"width": 39, "x": 514, "name": "rect", "height": 31, "y": 344}, "label": "H\u00e0"}, {"box": {"width": 48, "x": 554, "name": "rect", "height": 31, "y": 348}, "label": "N\u1ed9i"}], "ID": [{"box": {"width": 330, "x": 358, "name": "rect", "height": 47, "y": 136}, "label": "001180014439"}], "address": [{"box": {"width": 49, "x": 405, "name": "rect", "height": 36, "y": 397}, "label": "T\u1eadp"}, {"box": {"width": 42, "x": 455, "name": "rect", "height": 31, "y": 396}, "label": "th\u1ec3"}, {"box": {"width": 56, "x": 498, "name": "rect", "height": 27, "y": 401}, "label": "kh\u1ea3o"}, {"box": {"width": 42, "x": 557, "name": "rect", "height": 29, "y": 398}, "label": "s\u00e1t"}, {"box": {"width": 56, "x": 282, "name": "rect", "height": 31, "y": 426}, "label": "thi\u1ebft"}, {"box": {"width": 32, "x": 341, "name": "rect", "height": 33, "y": 424}, "label": "k\u1ebf"}, {"box": {"width": 50, "x": 374, "name": "rect", "height": 29, "y": 429}, "label": "\u0111i\u1ec7n"}, {"box": {"width": 52, "x": 434, "name": "rect", "height": 29, "y": 430}, "label": "V\u0103n"}, {"box": {"width": 66, "x": 488, "name": "rect", "height": 28, "y": 432}, "label": "Qu\u00e1n"}, {"box": {"width": 38, "x": 562, "name": "rect", "height": 33, "y": 429}, "label": "H\u00e0"}, {"box": {"width": 68, "x": 600, "name": "rect", "height": 35, "y": 432}, "label": "\u0110\u00f4ng"}, {"box": {"width": 40, "x": 674, "name": "rect", "height": 29, "y": 433}, "label": "H\u00e0"}, {"box": {"width": 47, "x": 716, "name": "rect", "height": 35, "y": 432}, "label": "N\u1ed9i"}], "DOB": [{"box": {"width": 137, "x": 474, "name": "rect", "height": 33, "y": 260}, "label": "26/03/1980"}], "file": "3191157_0923196671_CMND_MatTruoc.jpg", "name": [{"box": {"width": 70, "x": 345, "name": "rect", "height": 29, "y": 212}, "label": "NG\u00d4"}, {"box": {"width": 51, "x": 417, "name": "rect", "height": 34, "y": 214}, "label": "TH\u1eca"}, {"box": {"width": 96, "x": 468, "name": "rect", "height": 33, "y": 215}, "label": "THANH"}, {"box": {"width": 79, "x": 559, "name": "rect", "height": 32, "y": 211}, "label": "TH\u1ea2O"}]}