{"file": "3332030_0934982973_CMND_MatTruoc.jpg", "ID": [{"label": "035073000112", "box": {"name": "rect", "x": 377, "y": 145, "width": 337, "height": 39}}], "name": [{"label": "NGUY\u1ec4N", "box": {"name": "rect", "x": 389, "y": 222, "width": 123, "height": 32}}, {"label": "NG\u1eccC", "box": {"name": "rect", "x": 513, "y": 222, "width": 81, "height": 33}}, {"label": "MINH", "box": {"name": "rect", "x": 600, "y": 222, "width": 75, "height": 31}}], "DOB": [{"label": "07/08/1973", "box": {"name": "rect", "x": 486, "y": 309, "width": 138, "height": 28}}], "doe": [{"label": "28/07/2030", "box": {"name": "rect", "x": 154, "y": 464, "width": 134, "height": 35}}], "sex": [{"label": "Nam", "box": {"name": "rect", "x": 361, "y": 342, "width": 67, "height": 32}}], "home": [{"label": "Ti\u00ean", "box": {"name": "rect", "x": 531, "y": 369, "width": 55, "height": 31}}, {"label": "H\u00e0", "box": {"name": "rect", "x": 592, "y": 372, "width": 39, "height": 27}}, {"label": "Nam", "box": {"name": "rect", "x": 633, "y": 370, "width": 60, "height": 29}}], "address": [{"label": "S\u1ed1", "box": {"name": "rect", "x": 460, "y": 431, "width": 41, "height": 30}}, {"label": "14", "box": {"name": "rect", "x": 505, "y": 433, "width": 35, "height": 29}}, {"label": "Ng\u00f5", "box": {"name": "rect", "x": 541, "y": 435, "width": 45, "height": 31}}, {"label": "285", "box": {"name": "rect", "x": 590, "y": 435, "width": 53, "height": 27}}, {"label": "\u0110\u1ed9i", "box": {"name": "rect", "x": 644, "y": 436, "width": 44, "height": 27}}, {"label": "C\u1ea5n", "box": {"name": "rect", "x": 691, "y": 434, "width": 53, "height": 28}}, {"label": "Li\u1ec5u", "box": {"name": "rect", "x": 452, "y": 463, "width": 54, "height": 29}}, {"label": "Giai", "box": {"name": "rect", "x": 509, "y": 465, "width": 54, "height": 29}}, {"label": "Ba", "box": {"name": "rect", "x": 564, "y": 465, "width": 41, "height": 27}}, {"label": "\u0110\u00ecnh", "box": {"name": "rect", "x": 604, "y": 464, "width": 59, "height": 31}}, {"label": "H\u00e0", "box": {"name": "rect", "x": 675, "y": 463, "width": 38, "height": 31}}, {"label": "N\u1ed9i", "box": {"name": "rect", "x": 715, "y": 464, "width": 42, "height": 28}}]}