{"doe": [{"box": {"width": 118, "x": 186, "name": "rect", "height": 25, "y": 461}, "label": "29/11/2029"}], "sex": [{"box": {"width": 56, "x": 365, "name": "rect", "height": 31, "y": 313}, "label": "Nam"}], "home": [{"box": {"width": 31, "x": 411, "name": "rect", "height": 33, "y": 353}, "label": "L\u00ea"}, {"box": {"width": 55, "x": 446, "name": "rect", "height": 26, "y": 356}, "label": "B\u00ecnh"}, {"box": {"width": 41, "x": 511, "name": "rect", "height": 25, "y": 356}, "label": "C\u00e1i"}, {"box": {"width": 65, "x": 556, "name": "rect", "height": 33, "y": 353}, "label": "R\u0103ng"}, {"box": {"width": 41, "x": 626, "name": "rect", "height": 30, "y": 356}, "label": "TP"}, {"box": {"width": 49, "x": 677, "name": "rect", "height": 34, "y": 353}, "label": "C\u1ea7n"}, {"box": {"width": 51, "x": 730, "name": "rect", "height": 28, "y": 356}, "label": "Th\u01a1"}], "ID": [{"box": {"width": 325, "x": 367, "name": "rect", "height": 35, "y": 147}, "label": "092089000899"}], "address": [{"box": {"width": 72, "x": 452, "name": "rect", "height": 24, "y": 416}, "label": "208/7"}, {"box": {"width": 36, "x": 528, "name": "rect", "height": 23, "y": 417}, "label": "KV"}, {"box": {"width": 48, "x": 574, "name": "rect", "height": 23, "y": 418}, "label": "Y\u00ean"}, {"box": {"width": 68, "x": 625, "name": "rect", "height": 30, "y": 415}, "label": "Trung"}, {"box": {"width": 33, "x": 408, "name": "rect", "height": 28, "y": 443}, "label": "L\u00ea"}, {"box": {"width": 56, "x": 444, "name": "rect", "height": 26, "y": 444}, "label": "B\u00ecnh"}, {"box": {"width": 41, "x": 510, "name": "rect", "height": 23, "y": 446}, "label": "C\u00e1i"}, {"box": {"width": 67, "x": 553, "name": "rect", "height": 28, "y": 445}, "label": "R\u0103ng"}, {"box": {"width": 34, "x": 627, "name": "rect", "height": 26, "y": 446}, "label": "TP"}, {"box": {"width": 46, "x": 675, "name": "rect", "height": 26, "y": 444}, "label": "C\u1ea7n"}, {"box": {"width": 53, "x": 723, "name": "rect", "height": 27, "y": 443}, "label": "Th\u01a1"}], "DOB": [{"box": {"width": 131, "x": 483, "name": "rect", "height": 30, "y": 267}, "label": "29/11/1989"}], "file": "3426666_01224782245_CMND_MatTruoc.jpg", "name": [{"box": {"width": 114, "x": 402, "name": "rect", "height": 29, "y": 199}, "label": "NGUY\u1ec4N"}, {"box": {"width": 63, "x": 519, "name": "rect", "height": 31, "y": 196}, "label": "V\u0128NH"}, {"box": {"width": 100, "x": 586, "name": "rect", "height": 27, "y": 199}, "label": "TH\u00d4NG"}]}