{"doe": [{"box": {"width": 120, "x": 138, "name": "rect", "height": 30, "y": 461}, "label": "15/02/2039"}], "sex": [{"box": {"width": 58, "x": 345, "name": "rect", "height": 30, "y": 300}, "label": "Nam"}], "home": [{"box": {"width": 49, "x": 413, "name": "rect", "height": 30, "y": 350}, "label": "Kim"}, {"box": {"width": 61, "x": 465, "name": "rect", "height": 28, "y": 353}, "label": "S\u01a1n"}, {"box": {"width": 59, "x": 530, "name": "rect", "height": 30, "y": 351}, "label": "Ninh"}, {"box": {"width": 65, "x": 590, "name": "rect", "height": 32, "y": 351}, "label": "B\u00ecnh"}], "ID": [{"box": {"width": 338, "x": 350, "name": "rect", "height": 48, "y": 125}, "label": "001079009014"}], "address": [{"box": {"width": 70, "x": 433, "name": "rect", "height": 30, "y": 411}, "label": "425B"}, {"box": {"width": 67, "x": 507, "name": "rect", "height": 31, "y": 414}, "label": "B\u1ea1ch"}, {"box": {"width": 49, "x": 575, "name": "rect", "height": 32, "y": 413}, "label": "Mai"}, {"box": {"width": 97, "x": 324, "name": "rect", "height": 37, "y": 441}, "label": "Tr\u01b0\u01a1ng"}, {"box": {"width": 59, "x": 424, "name": "rect", "height": 34, "y": 446}, "label": "\u0110\u1ecbnh"}, {"box": {"width": 45, "x": 492, "name": "rect", "height": 30, "y": 446}, "label": "Hai"}, {"box": {"width": 35, "x": 541, "name": "rect", "height": 31, "y": 446}, "label": "B\u00e0"}, {"box": {"width": 78, "x": 580, "name": "rect", "height": 37, "y": 447}, "label": "Tr\u01b0ng"}, {"box": {"width": 41, "x": 666, "name": "rect", "height": 29, "y": 449}, "label": "H\u00e0"}, {"box": {"width": 44, "x": 710, "name": "rect", "height": 30, "y": 450}, "label": "N\u1ed9i"}], "DOB": [{"box": {"width": 144, "x": 462, "name": "rect", "height": 30, "y": 262}, "label": "15/02/1979"}], "file": "3479009_0922595973_CMND_MatTruoc.jpg", "name": [{"box": {"width": 41, "x": 412, "name": "rect", "height": 38, "y": 213}, "label": "L\u00ca"}, {"box": {"width": 40, "x": 457, "name": "rect", "height": 35, "y": 216}, "label": "V\u0168"}, {"box": {"width": 106, "x": 497, "name": "rect", "height": 32, "y": 219}, "label": "KH\u00c1NH"}]}