{"file": "3520443_01207432663_CMND_MatTruoc.jpg", "ID": [{"label": "031079002033", "box": {"name": "rect", "x": 358, "y": 137, "width": 334, "height": 38}}], "name": [{"label": "L\u01afU", "box": {"name": "rect", "x": 398, "y": 223, "width": 62, "height": 28}}, {"label": "V\u0102N", "box": {"name": "rect", "x": 464, "y": 223, "width": 59, "height": 28}}, {"label": "C\u01af\u1edcNG", "box": {"name": "rect", "x": 526, "y": 222, "width": 114, "height": 31}}], "DOB": [{"label": "02/02/1979", "box": {"name": "rect", "x": 476, "y": 304, "width": 138, "height": 32}}], "doe": [{"label": "11/12/2030", "box": {"name": "rect", "x": 160, "y": 454, "width": 114, "height": 32}}], "sex": [{"label": "Nam", "box": {"name": "rect", "x": 352, "y": 335, "width": 60, "height": 26}}], "home": [{"label": "H\u00f2a", "box": {"name": "rect", "x": 407, "y": 368, "width": 55, "height": 33}}, {"label": "An", "box": {"name": "rect", "x": 468, "y": 371, "width": 37, "height": 31}}, {"label": "D\u01b0\u01a1ng", "box": {"name": "rect", "x": 508, "y": 374, "width": 88, "height": 29}}, {"label": "H\u1ea3i", "box": {"name": "rect", "x": 608, "y": 372, "width": 45, "height": 30}}, {"label": "Ph\u00f2ng", "box": {"name": "rect", "x": 658, "y": 371, "width": 79, "height": 39}}], "address": [{"label": "Ng\u1ecd", "box": {"name": "rect", "x": 408, "y": 425, "width": 50, "height": 33}}, {"label": "D\u01b0\u01a1ng", "box": {"name": "rect", "x": 460, "y": 428, "width": 87, "height": 33}}, {"label": "4", "box": {"name": "rect", "x": 553, "y": 428, "width": 21, "height": 28}}, {"label": "An", "box": {"name": "rect", "x": 581, "y": 430, "width": 37, "height": 27}}, {"label": "H\u00f2a", "box": {"name": "rect", "x": 622, "y": 429, "width": 52, "height": 31}}, {"label": "An", "box": {"name": "rect", "x": 395, "y": 459, "width": 39, "height": 29}}, {"label": "D\u01b0\u01a1ng", "box": {"name": "rect", "x": 436, "y": 460, "width": 87, "height": 34}}, {"label": "H\u1ea3i", "box": {"name": "rect", "x": 531, "y": 460, "width": 46, "height": 29}}, {"label": "Ph\u00f2ng", "box": {"name": "rect", "x": 579, "y": 460, "width": 80, "height": 35}}]}